AUTHORS
CHANGELOG.txt
DESCRIPTION
LICENSE
MANIFEST.in
README.rst
setup.cfg
setup.py
dashboard_app/__init__.py
dashboard_app/admin.py
dashboard_app/dashboard_widgets.py
dashboard_app/decorators.py
dashboard_app/exceptions.py
dashboard_app/models.py
dashboard_app/settings.py
dashboard_app/urls.py
dashboard_app/view_mixins.py
dashboard_app/views.py
dashboard_app/widget_base.py
dashboard_app/widget_pool.py
dashboard_app/migrations/0001_initial.py
dashboard_app/migrations/__init__.py
dashboard_app/static/dashboard_app/css/styles.css
dashboard_app/static/dashboard_app/css/libs/bootstrap.css
dashboard_app/static/dashboard_app/fonts/glyphicons-halflings-regular.eot
dashboard_app/static/dashboard_app/fonts/glyphicons-halflings-regular.svg
dashboard_app/static/dashboard_app/fonts/glyphicons-halflings-regular.ttf
dashboard_app/static/dashboard_app/fonts/glyphicons-halflings-regular.woff
dashboard_app/static/dashboard_app/js/dashboard.js
dashboard_app/static/dashboard_app/js/libs/bootstrap.min.js
dashboard_app/templates/dashboard_app/dashboard.html
dashboard_app/templates/dashboard_app/partials/widget.html
dashboard_app/templates/dashboard_app/widgets/dummy_widget.html
dashboard_app/tests/.coverage
dashboard_app/tests/.coveragerc
dashboard_app/tests/__init__.py
dashboard_app/tests/factories.py
dashboard_app/tests/mixins.py
dashboard_app/tests/models_tests.py
dashboard_app/tests/runtests.py
dashboard_app/tests/south_settings.py
dashboard_app/tests/test_settings.py
dashboard_app/tests/urls.py
dashboard_app/tests/views_tests.py
dashboard_app/tests/widget_base_tests.py
dashboard_app/tests/widget_pool_tests.py
dashboard_app/tests/test_app/__init__.py
dashboard_app/tests/test_app/models.py
dashboard_app/tests/test_app/templates/400.html
dashboard_app/tests/test_app/templates/500.html
dashboard_app/tests/test_widget_app/__init__.py
dashboard_app/tests/test_widget_app/dashboard_widgets.py
dashboard_app/tests/test_widget_app/models.py
django_dashboard_app.egg-info/PKG-INFO
django_dashboard_app.egg-info/SOURCES.txt
django_dashboard_app.egg-info/dependency_links.txt
django_dashboard_app.egg-info/requires.txt
django_dashboard_app.egg-info/top_level.txt