Metadata-Version: 1.0
Name: django-dashboard-app
Version: 0.2.1
Summary: A reusable Django app for displaying a dashboard with a fluid grid of widgets.
